mt/geo/__init__.py
mt/geo/approximation.py
mt/geo/bounding.py
mt/geo/join_volume.py
mt/geo/object.py
mt/geo/transformation.py
mt/geo/version.py
mt/geo2d/__init__.py
mt/geo2d/affine.py
mt/geo2d/ellipse.py
mt/geo2d/iou.py
mt/geo2d/linear.py
mt/geo2d/moments.py
mt/geo2d/point.py
mt/geo2d/point_list.py
mt/geo2d/polygon.py
mt/geo2d/polygon_integral.py
mt/geo2d/rect.py
mt/geo2d/rect2oct.py
mt/geo2d/rrect.py
mt/geo2d/shapely.py
mt/geo2d/similarity2d.py
mt/geo3d/__init__.py
mt/geo3d/affine.py
mt/geo3d/box.py
mt/geo3d/ellipsoid.py
mt/geo3d/moments.py
mt/geo3d/point.py
mt/geo3d/point_list.py
mt/geond/__init__.py
mt/geond/affine.py
mt/geond/dilatation.py
mt/geond/dilated_isometry.py
mt/geond/dilated_translation.py
mt/geond/hyperbox.py
mt/geond/hypercube.py
mt/geond/hyperellipsoid.py
mt/geond/iou.py
mt/geond/isometry.py
mt/geond/moments.py
mt/geond/point.py
mt/geond/point_list.py
mtgeo-1.1.15.dist-info/METADATA
mtgeo-1.1.15.dist-info/WHEEL
mtgeo-1.1.15.dist-info/top_level.txt
mtgeo-1.1.15.dist-info/RECORD
