Metadata-Version: 2.4
Name: mtgeo
Version: 1.1.15
Summary: The most fundamental geometric modules in Python for Minh-Tri Pham
Home-page: https://github.com/inteplus/mtgeo
Author: Minh-Tri Pham
Project-URL: Documentation, https://mtdoc.readthedocs.io/en/latest/mt.geo/mt.geo.html
Project-URL: Source Code, https://github.com/inteplus/mtgeo
Requires-Dist: mtbase>=4.33.2
Requires-Dist: mtglm>=0.1
Requires-Dist: mttf
Dynamic: author
Dynamic: home-page
Dynamic: project-url
Dynamic: requires-dist
Dynamic: summary
